Metadata-Version: 2.4
Name: ohdsi-circe-python-alpha
Version: 0.1.0
Summary: Python implementation of OHDSI CIRCE-BE for cohort definition and SQL generation
Author-email: Jamie Gilbert <gilbert@ohdsi.org>
Maintainer-email: Jamie Gilbert <gilbert@ohdsi.org>
License: Apache-2.0
Project-URL: Homepage, https://github.com/OHDSI/Circepy
Project-URL: Documentation, https://ohdsi-circe-python-alpha.readthedocs.io/
Project-URL: Repository, https://github.com/OHDSI/Circepy.git
Project-URL: Issues, https://github.com/OHDSI/Circepy/issues
Project-URL: Changelog, https://github.com/OHDSI/Circepy/blob/main/CHANGELOG.md
Project-URL: Bug Tracker, https://github.com/OHDSI/Circepy/issues
Project-URL: Source Code, https://github.com/OHDSI/Circepy
Keywords: ohdsi,circe,cohort,sql,omop,cdm,healthcare,observational-health
Classifier: Development Status :: 3 - Alpha
Classifier: Intended Audience :: Healthcare Industry
Classifier: Intended Audience :: Science/Research
Classifier: License :: OSI Approved :: Apache Software License
Classifier: Operating System :: OS Independent
Classifier: Programming Language :: Python :: 3
Classifier: Programming Language :: Python :: 3.8
Classifier: Programming Language :: Python :: 3.9
Classifier: Programming Language :: Python :: 3.10
Classifier: Programming Language :: Python :: 3.11
Classifier: Programming Language :: Python :: 3.12
Classifier: Topic :: Scientific/Engineering :: Medical Science Apps.
Classifier: Topic :: Software Development :: Libraries :: Python Modules
Classifier: Typing :: Typed
Requires-Python: >=3.8
License-File: LICENSE
Requires-Dist: pydantic>=2.0.0
Requires-Dist: typing-extensions>=4.0.0
Requires-Dist: jinja2>=3.1.0
Provides-Extra: dev
Requires-Dist: pytest>=7.0.0; extra == "dev"
Requires-Dist: pytest-cov>=4.0.0; extra == "dev"
Requires-Dist: black>=22.0.0; extra == "dev"
Requires-Dist: isort>=5.0.0; extra == "dev"
Requires-Dist: flake8>=5.0.0; extra == "dev"
Requires-Dist: mypy>=1.0.0; extra == "dev"
Requires-Dist: sqlglot>=23.0.0; extra == "dev"
Requires-Dist: duckdb>=0.9.0; extra == "dev"
Provides-Extra: docs
Requires-Dist: sphinx>=5.0.0; extra == "docs"
Requires-Dist: sphinx-rtd-theme>=1.0.0; extra == "docs"
Dynamic: license-file
